sstash
