Metadata-Version: 1.1
Name: sstash
Version: 0.17
Summary: A simple on-disk secure stash for secrets
Home-page: https://github.com/realcr/sstash
Author: real
Author-email: realcr@gmail.com
License: MIT
Keywords: sstash secure stash secret on-disk
Platform: UNKNOWN
Classifier: Development Status :: 4 - Beta
Classifier: License :: OSI Approved :: MIT License
Classifier: Programming Language :: Python :: 3.5
Classifier: Topic :: Security
